<annotation>
    <folder>First 10 rows</folder>
    <filename>BF_ST_002_APT_004Day1.jpg</filename>
    <size>
        <width>324</width>
        <height>300</height>
        <depth>3</depth>
    </size>
    <segmented>0</segmented>
    <object>
        <name>Cell</name>
        <pose>Unspecified</pose>
        <truncated>0</truncated>
        <occluded>0</occluded>
        <difficult>0</difficult>
        <polygon>
            <x1>162</x1>
            <y1>246</y1>
            <x2>166</x2>
            <y2>249</y2>
            <x3>168</x3>
            <y3>253</y3>
            <x4>168</x4>
            <y4>257</y4>
            <x5>164</x5>
            <y5>261</y5>
            <x6>156</x6>
            <y6>260</y6>
            <x7>153</x7>
            <y7>256</y7>
            <x8>152</x8>
            <y8>250</y8>
            <x9>156</x9>
            <y9>247</y9>
        </polygon>
    </object>
    <object>
        <name>CellClump</name>
        <pose>Unspecified</pose>
        <truncated>0</truncated>
        <occluded>0</occluded>
        <difficult>0</difficult>
        <polygon>
            <x1>162</x1>
            <y1>246</y1>
            <x2>166</x2>
            <y2>249</y2>
            <x3>168</x3>
            <y3>253</y3>
            <x4>168</x4>
            <y4>257</y4>
            <x5>164</x5>
            <y5>261</y5>
            <x6>156</x6>
            <y6>260</y6>
            <x7>153</x7>
            <y7>256</y7>
            <x8>152</x8>
            <y8>250</y8>
            <x9>156</x9>
            <y9>247</y9>
        </polygon>
    </object>
    <object>
        <name>CellClump</name>
        <pose>Unspecified</pose>
        <truncated>0</truncated>
        <occluded>0</occluded>
        <difficult>0</difficult>
        <polygon>
            <x1>213</x1>
            <y1>35</y1>
            <x2>216</x2>
            <y2>39</y2>
            <x3>217</x3>
            <y3>43</y3>
            <x4>214</x4>
            <y4>47</y4>
            <x5>206</x5>
            <y5>49</y5>
            <x6>202</x6>
            <y6>47</y6>
            <x7>199</x7>
            <y7>44</y7>
            <x8>199</x8>
            <y8>40</y8>
            <x9>194</x9>
            <y9>40</y9>
            <x10>191</x10>
            <y10>38</y10>
            <x11>188</x11>
            <y11>40</y11>
            <x12>183</x12>
            <y12>41</y12>
            <x13>178</x13>
            <y13>41</y13>
            <x14>174</x14>
            <y14>38</y14>
            <x15>170</x15>
            <y15>42</y15>
            <x16>161</x16>
            <y16>43</y16>
            <x17>157</x17>
            <y17>42</y17>
            <x18>155</x18>
            <y18>43</y18>
            <x19>149</x19>
            <y19>44</y19>
            <x20>143</x20>
            <y20>41</y20>
            <x21>141</x21>
            <y21>38</y21>
            <x22>138</x22>
            <y22>36</y22>
            <x23>134</x23>
            <y23>39</y23>
            <x24>127</x24>
            <y24>38</y24>
            <x25>124</x25>
            <y25>34</y25>
            <x26>124</x26>
            <y26>29</y26>
            <x27>135</x27>
            <y27>22</y27>
            <x28>200</x28>
            <y28>24</y28>
            <x29>205</x29>
            <y29>27</y29>
        </polygon>
    </object>
    <object>
        <name>Cell</name>
        <pose>Unspecified</pose>
        <truncated>0</truncated>
        <occluded>0</occluded>
        <difficult>0</difficult>
        <polygon>
            <x1>150</x1>
            <y1>23</y1>
            <x2>153</x2>
            <y2>27</y2>
            <x3>154</x3>
            <y3>32</y3>
            <x4>152</x4>
            <y4>36</y4>
            <x5>144</x5>
            <y5>38</y5>
            <x6>139</x6>
            <y6>37</y6>
            <x7>136</x7>
            <y7>34</y7>
            <x8>133</x8>
            <y8>30</y8>
            <x9>133</x9>
            <y9>25</y9>
            <x10>138</x10>
            <y10>22</y10>
            <x11>143</x11>
            <y11>22</y11>
            <x12>147</x12>
            <y12>22</y12>
        </polygon>
    </object>
    <object>
        <name>Cell</name>
        <pose>Unspecified</pose>
        <truncated>0</truncated>
        <occluded>0</occluded>
        <difficult>0</difficult>
        <polygon>
            <x1>139</x1>
            <y1>22</y1>
            <x2>144</x2>
            <y2>26</y2>
            <x3>144</x3>
            <y3>31</y3>
            <x4>141</x4>
            <y4>36</y4>
            <x5>135</x5>
            <y5>39</y5>
            <x6>128</x6>
            <y6>39</y6>
            <x7>125</x7>
            <y7>35</y7>
            <x8>125</x8>
            <y8>29</y8>
            <x9>129</x9>
            <y9>25</y9>
            <x10>133</x10>
            <y10>22</y10>
        </polygon>
    </object>
    <object>
        <name>Cell</name>
        <pose>Unspecified</pose>
        <truncated>0</truncated>
        <occluded>0</occluded>
        <difficult>0</difficult>
        <polygon>
            <x1>158</x1>
            <y1>24</y1>
            <x2>161</x2>
            <y2>29</y2>
            <x3>161</x3>
            <y3>35</y3>
            <x4>159</x4>
            <y4>40</y4>
            <x5>154</x5>
            <y5>44</y5>
            <x6>149</x6>
            <y6>44</y6>
            <x7>143</x7>
            <y7>40</y7>
            <x8>141</x8>
            <y8>37</y8>
            <x9>140</x9>
            <y9>32</y9>
            <x10>144</x10>
            <y10>25</y10>
            <x11>152</x11>
            <y11>22</y11>
        </polygon>
    </object>
    <object>
        <name>Cell</name>
        <pose>Unspecified</pose>
        <truncated>0</truncated>
        <occluded>0</occluded>
        <difficult>0</difficult>
        <polygon>
            <x1>171</x1>
            <y1>24</y1>
            <x2>174</x2>
            <y2>29</y2>
            <x3>175</x3>
            <y3>35</y3>
            <x4>174</x4>
            <y4>39</y4>
            <x5>169</x5>
            <y5>43</y5>
            <x6>163</x6>
            <y6>44</y6>
            <x7>158</x7>
            <y7>43</y7>
            <x8>152</x8>
            <y8>37</y8>
            <x9>152</x9>
            <y9>31</y9>
            <x10>155</x10>
            <y10>26</y10>
            <x11>160</x11>
            <y11>23</y11>
            <x12>165</x12>
            <y12>23</y12>
        </polygon>
    </object>
    <object>
        <name>Cell</name>
        <pose>Unspecified</pose>
        <truncated>0</truncated>
        <occluded>0</occluded>
        <difficult>0</difficult>
        <polygon>
            <x1>192</x1>
            <y1>24</y1>
            <x2>195</x2>
            <y2>28</y2>
            <x3>195</x3>
            <y3>32</y3>
            <x4>192</x4>
            <y4>37</y4>
            <x5>189</x5>
            <y5>40</y5>
            <x6>182</x6>
            <y6>42</y6>
            <x7>176</x7>
            <y7>41</y7>
            <x8>174</x8>
            <y8>36</y8>
            <x9>173</x9>
            <y9>29</y9>
            <x10>176</x10>
            <y10>24</y10>
            <x11>182</x11>
            <y11>23</y11>
            <x12>187</x12>
            <y12>23</y12>
        </polygon>
    </object>
    <object>
        <name>Cell</name>
        <pose>Unspecified</pose>
        <truncated>0</truncated>
        <occluded>0</occluded>
        <difficult>0</difficult>
        <polygon>
            <x1>203</x1>
            <y1>25</y1>
            <x2>206</x2>
            <y2>28</y2>
            <x3>207</x3>
            <y3>31</y3>
            <x4>204</x4>
            <y4>36</y4>
            <x5>200</x5>
            <y5>40</y5>
            <x6>195</x6>
            <y6>40</y6>
            <x7>191</x7>
            <y7>37</y7>
            <x8>189</x8>
            <y8>31</y8>
            <x9>191</x9>
            <y9>27</y9>
            <x10>197</x10>
            <y10>24</y10>
        </polygon>
    </object>
    <object>
        <name>Cell</name>
        <pose>Unspecified</pose>
        <truncated>0</truncated>
        <occluded>0</occluded>
        <difficult>0</difficult>
        <polygon>
            <x1>210</x1>
            <y1>32</y1>
            <x2>214</x2>
            <y2>35</y2>
            <x3>217</x3>
            <y3>38</y3>
            <x4>217</x4>
            <y4>42</y4>
            <x5>214</x5>
            <y5>46</y5>
            <x6>208</x6>
            <y6>49</y6>
            <x7>204</x7>
            <y7>49</y7>
            <x8>200</x8>
            <y8>46</y8>
            <x9>199</x9>
            <y9>40</y9>
            <x10>202</x10>
            <y10>36</y10>
            <x11>206</x11>
            <y11>33</y11>
        </polygon>
    </object>
    <object>
        <name>Trap</name>
        <pose>Unspecified</pose>
        <truncated>0</truncated>
        <occluded>0</occluded>
        <difficult>0</difficult>
        <bndbox>
            <xmin>139</xmin>
            <ymin>241</ymin>
            <xmax>183</xmax>
            <ymax>283</ymax>
        </bndbox>
    </object>
    <object>
        <name>Channel</name>
        <pose>Unspecified</pose>
        <truncated>0</truncated>
        <occluded>0</occluded>
        <difficult>0</difficult>
        <polygon>
            <x1>324</x1>
            <y1>121</y1>
            <x2>301</x2>
            <y2>121</y2>
            <x3>294</x3>
            <y3>120</y3>
            <x4>286</x4>
            <y4>121</y4>
            <x5>279</x5>
            <y5>123</y5>
            <x6>270</x6>
            <y6>127</y6>
            <x7>261</x7>
            <y7>136</y7>
            <x8>257</x8>
            <y8>146</y8>
            <x9>255</x9>
            <y9>160</y9>
            <x10>256</x10>
            <y10>172</y10>
            <x11>263</x11>
            <y11>183</y11>
            <x12>270</x12>
            <y12>191</y12>
            <x13>277</x13>
            <y13>195</y13>
            <x14>285</x14>
            <y14>197</y14>
            <x15>292</x15>
            <y15>198</y15>
            <x16>297</x16>
            <y16>198</y16>
            <x17>302</x17>
            <y17>198</y17>
            <x18>305</x18>
            <y18>199</y18>
            <x19>307</x19>
            <y19>201</y19>
            <x20>307</x20>
            <y20>206</y20>
            <x21>307</x21>
            <y21>211</y21>
            <x22>302</x22>
            <y22>219</y22>
            <x23>297</x23>
            <y23>223</y23>
            <x24>160</x24>
            <y24>253</y24>
            <x25>40</x25>
            <y25>219</y25>
            <x26>29</x26>
            <y26>216</y26>
            <x27>24</x27>
            <y27>215</y27>
            <x28>22</x28>
            <y28>212</y28>
            <x29>18</x29>
            <y29>206</y29>
            <x30>17</x30>
            <y30>199</y30>
            <x31>17</x31>
            <y31>191</y31>
            <x32>16</x32>
            <y32>182</y32>
            <x33>12</x33>
            <y33>175</y33>
            <x34>8</x34>
            <y34>169</y34>
            <x35>4</x35>
            <y35>165</y35>
            <x36>1</x36>
            <y36>163</y36>
            <x37>1</x37>
            <y37>258</y37>
            <x38>33</x38>
            <y38>258</y38>
            <x39>39</x39>
            <y39>265</y39>
            <x40>41</x40>
            <y40>259</y40>
            <x41>45</x41>
            <y41>257</y41>
            <x42>136</x42>
            <y42>283</y42>
            <x43>139</x43>
            <y43>286</y43>
            <x44>141</x44>
            <y44>289</y44>
            <x45>143</x45>
            <y45>294</y45>
            <x46>143</x46>
            <y46>300</y46>
            <x47>159</x47>
            <y47>300</y47>
            <x48>175</x48>
            <y48>300</y48>
            <x49>176</x49>
            <y49>293</y49>
            <x50>178</x50>
            <y50>290</y50>
            <x51>182</x51>
            <y51>285</y51>
            <x52>185</x52>
            <y52>283</y52>
            <x53>275</x53>
            <y53>264</y53>
            <x54>280</x54>
            <y54>266</y54>
            <x55>280</x55>
            <y55>271</y55>
            <x56>287</x56>
            <y56>266</y56>
            <x57>324</x57>
            <y57>267</y57>
            <x58>324</x58>
            <y58>173</y58>
            <x59>321</x59>
            <y59>171</y59>
            <x60>316</x60>
            <y60>169</y60>
            <x61>311</x61>
            <y61>166</y61>
            <x62>304</x62>
            <y62>166</y62>
            <x63>295</x63>
            <y63>166</y63>
            <x64>291</x64>
            <y64>165</y64>
            <x65>288</x65>
            <y65>162</y65>
            <x66>288</x66>
            <y66>159</y66>
            <x67>289</x67>
            <y67>155</y67>
            <x68>292</x68>
            <y68>154</y68>
            <x69>295</x69>
            <y69>153</y69>
            <x70>324</x70>
            <y70>154</y70>
        </polygon>
    </object>
    <object>
        <name>Channel</name>
        <pose>Unspecified</pose>
        <truncated>0</truncated>
        <occluded>0</occluded>
        <difficult>0</difficult>
        <polygon>
            <x1>1</x1>
            <y1>1</y1>
            <x2>13</x2>
            <y2>1</y2>
            <x3>28</x3>
            <y3>1</y3>
            <x4>290</x4>
            <y4>1</y4>
            <x5>324</x5>
            <y5>10</y5>
            <x6>324</x6>
            <y6>102</y6>
            <x7>315</x7>
            <y7>91</y7>
            <x8>311</x8>
            <y8>80</y8>
            <x9>310</x9>
            <y9>70</y9>
            <x10>310</x10>
            <y10>64</y10>
            <x11>310</x11>
            <y11>57</y11>
            <x12>310</x12>
            <y12>53</y12>
            <x13>309</x13>
            <y13>49</y13>
            <x14>308</x14>
            <y14>46</y14>
            <x15>304</x15>
            <y15>42</y15>
            <x16>299</x16>
            <y16>39</y16>
            <x17>213</x17>
            <y17>16</y17>
            <x18>209</x18>
            <y18>17</y18>
            <x19>208</x19>
            <y19>22</y19>
            <x20>200</x20>
            <y20>16</y20>
            <x21>134</x21>
            <y21>14</y21>
            <x22>128</x22>
            <y22>20</y22>
            <x23>126</x23>
            <y23>15</y23>
            <x24>123</x24>
            <y24>13</y24>
            <x25>31</x25>
            <y25>33</y25>
            <x26>26</x26>
            <y26>37</y26>
            <x27>22</x27>
            <y27>44</y27>
            <x28>22</x28>
            <y28>65</y28>
            <x29>24</x29>
            <y29>67</y29>
            <x30>29</x30>
            <y30>68</y30>
            <x31>44</x31>
            <y31>69</y31>
            <x32>55</x32>
            <y32>74</y32>
            <x33>64</x33>
            <y33>81</y33>
            <x34>70</x34>
            <y34>89</y34>
            <x35>73</x35>
            <y35>98</y35>
            <x36>74</x36>
            <y36>106</y36>
            <x37>73</x37>
            <y37>116</y37>
            <x38>70</x38>
            <y38>123</y38>
            <x39>66</x39>
            <y39>130</y39>
            <x40>60</x40>
            <y40>136</y40>
            <x41>54</x41>
            <y41>140</y41>
            <x42>49</x42>
            <y42>143</y42>
            <x43>45</x43>
            <y43>145</y43>
            <x44>39</x44>
            <y44>145</y44>
            <x45>1</x45>
            <y45>145</y45>
            <x46>1</x46>
            <y46>113</y46>
            <x47>31</x47>
            <y47>113</y47>
            <x48>35</x48>
            <y48>113</y48>
            <x49>39</x49>
            <y49>112</y49>
            <x50>40</x50>
            <y50>109</y50>
            <x51>41</x51>
            <y51>106</y51>
            <x52>40</x52>
            <y52>103</y52>
            <x53>37</x53>
            <y53>101</y53>
            <x54>23</x54>
            <y54>101</y54>
            <x55>13</x55>
            <y55>99</y55>
            <x56>6</x56>
            <y56>95</y56>
            <x57>1</x57>
            <y57>91</y57>
        </polygon>
    </object>
    <object>
        <name>Marker</name>
        <pose>Unspecified</pose>
        <truncated>0</truncated>
        <occluded>0</occluded>
        <difficult>0</difficult>
        <bndbox>
            <xmin>239</xmin>
            <ymin>195</ymin>
            <xmax>269</xmax>
            <ymax>222</ymax>
        </bndbox>
    </object>
    <object>
        <name>StNum</name>
        <pose>Unspecified</pose>
        <truncated>0</truncated>
        <occluded>0</occluded>
        <difficult>0</difficult>
        <bndbox>
            <xmin>19</xmin>
            <ymin>159</ymin>
            <xmax>81</xmax>
            <ymax>209</ymax>
        </bndbox>
    </object>
    <object>
        <name>AptNum</name>
        <pose>Unspecified</pose>
        <truncated>0</truncated>
        <occluded>0</occluded>
        <difficult>0</difficult>
        <bndbox>
            <xmin>246</xmin>
            <ymin>48</ymin>
            <xmax>308</xmax>
            <ymax>93</ymax>
        </bndbox>
    </object>
    <object>
        <name>Chamber</name>
        <pose>Unspecified</pose>
        <truncated>0</truncated>
        <occluded>0</occluded>
        <difficult>0</difficult>
        <polygon>
            <x1>200</x1>
            <y1>16</y1>
            <x2>207</x2>
            <y2>28</y2>
            <x3>217</x3>
            <y3>38</y3>
            <x4>227</x4>
            <y4>49</y4>
            <x5>234</x5>
            <y5>59</y5>
            <x6>240</x6>
            <y6>72</y6>
            <x7>245</x7>
            <y7>92</y7>
            <x8>244</x8>
            <y8>141</y8>
            <x9>243</x9>
            <y9>152</y9>
            <x10>238</x10>
            <y10>167</y10>
            <x11>234</x11>
            <y11>174</y11>
            <x12>229</x12>
            <y12>182</y12>
            <x13>224</x13>
            <y13>189</y13>
            <x14>218</x14>
            <y14>195</y14>
            <x15>163</x15>
            <y15>241</y15>
            <x16>158</x16>
            <y16>241</y16>
            <x17>104</x17>
            <y17>188</y17>
            <x18>95</x18>
            <y18>177</y18>
            <x19>88</x19>
            <y19>161</y19>
            <x20>84</x20>
            <y20>148</y20>
            <x21>83</x21>
            <y21>135</y21>
            <x22>83</x22>
            <y22>123</y22>
            <x23>85</x23>
            <y23>89</y23>
            <x24>88</x24>
            <y24>74</y24>
            <x25>93</x25>
            <y25>62</y25>
            <x26>100</x26>
            <y26>51</y26>
            <x27>107</x27>
            <y27>43</y27>
            <x28>117</x28>
            <y28>34</y28>
            <x29>125</x29>
            <y29>26</y29>
            <x30>133</x30>
            <y30>14</y30>
        </polygon>
    </object>
</annotation>