<annotation>
    <folder>First 10 rows</folder>
    <filename>BF_ST_002_APT_010Day0.jpg</filename>
    <size>
        <width>324</width>
        <height>300</height>
        <depth>3</depth>
    </size>
    <segmented>0</segmented>
    <object>
        <name>CellClump</name>
        <pose>Unspecified</pose>
        <truncated>0</truncated>
        <occluded>0</occluded>
        <difficult>0</difficult>
        <polygon>
            <x1>148</x1>
            <y1>40</y1>
            <x2>151</x2>
            <y2>39</y2>
            <x3>153</x3>
            <y3>38</y3>
            <x4>155</x4>
            <y4>36</y4>
            <x5>156</x5>
            <y5>35</y5>
            <x6>156</x6>
            <y6>33</y6>
            <x7>156</x7>
            <y7>30</y7>
            <x8>155</x8>
            <y8>29</y8>
            <x9>153</x9>
            <y9>28</y9>
            <x10>151</x10>
            <y10>27</y10>
            <x11>150</x11>
            <y11>27</y11>
            <x12>148</x12>
            <y12>27</y12>
            <x13>146</x13>
            <y13>28</y13>
            <x14>145</x14>
            <y14>29</y14>
            <x15>145</x15>
            <y15>29</y15>
            <x16>144</x16>
            <y16>28</y16>
            <x17>142</x17>
            <y17>27</y17>
            <x18>139</x18>
            <y18>27</y18>
            <x19>136</x19>
            <y19>27</y19>
            <x20>133</x20>
            <y20>28</y20>
            <x21>132</x21>
            <y21>29</y21>
            <x22>131</x22>
            <y22>31</y22>
            <x23>131</x23>
            <y23>33</y23>
            <x24>131</x24>
            <y24>35</y24>
            <x25>132</x25>
            <y25>36</y25>
            <x26>135</x26>
            <y26>38</y26>
            <x27>137</x27>
            <y27>39</y27>
            <x28>139</x28>
            <y28>39</y28>
            <x29>141</x29>
            <y29>38</y29>
            <x30>143</x30>
            <y30>37</y30>
            <x31>144</x31>
            <y31>38</y31>
            <x32>144</x32>
            <y32>38</y32>
            <x33>145</x33>
            <y33>39</y33>
        </polygon>
    </object>
    <object>
        <name>Cell</name>
        <pose>Unspecified</pose>
        <truncated>0</truncated>
        <occluded>0</occluded>
        <difficult>0</difficult>
        <polygon>
            <x1>146</x1>
            <y1>33</y1>
            <x2>146</x2>
            <y2>31</y2>
            <x3>145</x3>
            <y3>29</y3>
            <x4>142</x4>
            <y4>27</y4>
            <x5>136</x5>
            <y5>27</y5>
            <x6>133</x6>
            <y6>28</y6>
            <x7>131</x7>
            <y7>30</y7>
            <x8>131</x8>
            <y8>33</y8>
            <x9>132</x9>
            <y9>36</y9>
            <x10>135</x10>
            <y10>38</y10>
            <x11>139</x11>
            <y11>39</y11>
            <x12>142</x12>
            <y12>38</y12>
            <x13>145</x13>
            <y13>36</y13>
        </polygon>
    </object>
    <object>
        <name>Cell</name>
        <pose>Unspecified</pose>
        <truncated>0</truncated>
        <occluded>0</occluded>
        <difficult>0</difficult>
        <polygon>
            <x1>156</x1>
            <y1>30</y1>
            <x2>156</x2>
            <y2>35</y2>
            <x3>154</x3>
            <y3>38</y3>
            <x4>149</x4>
            <y4>40</y4>
            <x5>144</x5>
            <y5>38</y5>
            <x6>144</x6>
            <y6>34</y6>
            <x7>145</x7>
            <y7>29</y7>
            <x8>148</x8>
            <y8>27</y8>
            <x9>152</x9>
            <y9>27</y9>
        </polygon>
    </object>
    <object>
        <name>Trap</name>
        <pose>Unspecified</pose>
        <truncated>0</truncated>
        <occluded>0</occluded>
        <difficult>0</difficult>
        <bndbox>
            <xmin>139</xmin>
            <ymin>245</ymin>
            <xmax>183</xmax>
            <ymax>287</ymax>
        </bndbox>
    </object>
    <object>
        <name>Channel</name>
        <pose>Unspecified</pose>
        <truncated>0</truncated>
        <occluded>0</occluded>
        <difficult>0</difficult>
        <polygon>
            <x1>324</x1>
            <y1>124</y1>
            <x2>301</x2>
            <y2>124</y2>
            <x3>293</x3>
            <y3>124</y3>
            <x4>285</x4>
            <y4>125</y4>
            <x5>278</x5>
            <y5>126</y5>
            <x6>270</x6>
            <y6>131</y6>
            <x7>261</x7>
            <y7>140</y7>
            <x8>256</x8>
            <y8>149</y8>
            <x9>254</x9>
            <y9>160</y9>
            <x10>255</x10>
            <y10>173</y10>
            <x11>260</x11>
            <y11>183</y11>
            <x12>266</x12>
            <y12>190</y12>
            <x13>274</x13>
            <y13>196</y13>
            <x14>283</x14>
            <y14>200</y14>
            <x15>291</x15>
            <y15>201</y15>
            <x16>297</x16>
            <y16>201</y16>
            <x17>303</x17>
            <y17>201</y17>
            <x18>306</x18>
            <y18>202</y18>
            <x19>306</x19>
            <y19>205</y19>
            <x20>306</x20>
            <y20>209</y20>
            <x21>306</x21>
            <y21>214</y21>
            <x22>304</x22>
            <y22>219</y22>
            <x23>298</x23>
            <y23>225</y23>
            <x24>161</x24>
            <y24>258</y24>
            <x25>38</x25>
            <y25>225</y25>
            <x26>28</x26>
            <y26>222</y26>
            <x27>25</x27>
            <y27>220</y27>
            <x28>21</x28>
            <y28>216</y28>
            <x29>19</x29>
            <y29>212</y29>
            <x30>18</x30>
            <y30>208</y30>
            <x31>18</x31>
            <y31>194</y31>
            <x32>16</x32>
            <y32>186</y32>
            <x33>12</x33>
            <y33>179</y33>
            <x34>7</x34>
            <y34>174</y34>
            <x35>4</x35>
            <y35>170</y35>
            <x36>1</x36>
            <y36>169</y36>
            <x37>1</x37>
            <y37>265</y37>
            <x38>34</x38>
            <y38>264</y38>
            <x39>41</x39>
            <y39>271</y39>
            <x40>42</x40>
            <y40>266</y40>
            <x41>46</x41>
            <y41>264</y41>
            <x42>136</x42>
            <y42>288</y42>
            <x43>140</x43>
            <y43>290</y43>
            <x44>142</x44>
            <y44>293</y44>
            <x45>144</x45>
            <y45>297</y45>
            <x46>144</x46>
            <y46>300</y46>
            <x47>162</x47>
            <y47>300</y47>
            <x48>178</x48>
            <y48>300</y48>
            <x49>178</x49>
            <y49>297</y49>
            <x50>181</x50>
            <y50>292</y50>
            <x51>185</x51>
            <y51>289</y51>
            <x52>188</x52>
            <y52>287</y52>
            <x53>277</x53>
            <y53>267</y53>
            <x54>281</x54>
            <y54>270</y54>
            <x55>281</x55>
            <y55>275</y55>
            <x56>289</x56>
            <y56>269</y56>
            <x57>324</x57>
            <y57>269</y57>
            <x58>324</x58>
            <y58>176</y58>
            <x59>321</x59>
            <y59>173</y59>
            <x60>315</x60>
            <y60>170</y60>
            <x61>310</x61>
            <y61>169</y61>
            <x62>303</x62>
            <y62>169</y62>
            <x63>295</x63>
            <y63>168</y63>
            <x64>292</x64>
            <y64>168</y64>
            <x65>289</x65>
            <y65>166</y65>
            <x66>287</x66>
            <y66>164</y66>
            <x67>287</x67>
            <y67>160</y67>
            <x68>290</x68>
            <y68>157</y68>
            <x69>295</x69>
            <y69>156</y69>
            <x70>324</x70>
            <y70>156</y70>
        </polygon>
    </object>
    <object>
        <name>Channel</name>
        <pose>Unspecified</pose>
        <truncated>0</truncated>
        <occluded>0</occluded>
        <difficult>0</difficult>
        <polygon>
            <x1>1</x1>
            <y1>11</y1>
            <x2>13</x2>
            <y2>8</y2>
            <x3>42</x3>
            <y3>1</y3>
            <x4>277</x4>
            <y4>1</y4>
            <x5>324</x5>
            <y5>14</y5>
            <x6>324</x6>
            <y6>105</y6>
            <x7>315</x7>
            <y7>97</y7>
            <x8>311</x8>
            <y8>87</y8>
            <x9>309</x9>
            <y9>77</y9>
            <x10>309</x10>
            <y10>71</y10>
            <x11>309</x11>
            <y11>64</y11>
            <x12>309</x12>
            <y12>59</y12>
            <x13>309</x13>
            <y13>55</y13>
            <x14>308</x14>
            <y14>51</y14>
            <x15>305</x15>
            <y15>47</y15>
            <x16>298</x16>
            <y16>43</y16>
            <x17>212</x17>
            <y17>20</y17>
            <x18>208</x18>
            <y18>21</y18>
            <x19>206</x19>
            <y19>26</y19>
            <x20>198</x20>
            <y20>21</y20>
            <x21>132</x21>
            <y21>20</y21>
            <x22>126</x22>
            <y22>26</y22>
            <x23>125</x23>
            <y23>21</y23>
            <x24>121</x24>
            <y24>19</y24>
            <x25>29</x25>
            <y25>40</y25>
            <x26>25</x26>
            <y26>44</y26>
            <x27>21</x27>
            <y27>49</y27>
            <x28>21</x28>
            <y28>71</y28>
            <x29>23</x29>
            <y29>74</y29>
            <x30>29</x30>
            <y30>74</y30>
            <x31>44</x31>
            <y31>75</y31>
            <x32>56</x32>
            <y32>81</y32>
            <x33>65</x33>
            <y33>89</y33>
            <x34>70</x34>
            <y34>97</y34>
            <x35>73</x35>
            <y35>105</y35>
            <x36>73</x36>
            <y36>113</y36>
            <x37>73</x37>
            <y37>123</y37>
            <x38>70</x38>
            <y38>130</y38>
            <x39>65</x39>
            <y39>137</y39>
            <x40>58</x40>
            <y40>144</y40>
            <x41>53</x41>
            <y41>147</y41>
            <x42>48</x42>
            <y42>149</y42>
            <x43>43</x43>
            <y43>151</y43>
            <x44>38</x44>
            <y44>152</y44>
            <x45>1</x45>
            <y45>151</y45>
            <x46>1</x46>
            <y46>119</y46>
            <x47>31</x47>
            <y47>119</y47>
            <x48>36</x48>
            <y48>119</y48>
            <x49>38</x49>
            <y49>118</y49>
            <x50>40</x50>
            <y50>115</y50>
            <x51>40</x51>
            <y51>112</y51>
            <x52>39</x52>
            <y52>109</y52>
            <x53>36</x53>
            <y53>107</y53>
            <x54>23</x54>
            <y54>107</y54>
            <x55>13</x55>
            <y55>105</y55>
            <x56>6</x56>
            <y56>102</y56>
            <x57>1</x57>
            <y57>98</y57>
        </polygon>
    </object>
    <object>
        <name>Marker</name>
        <pose>Unspecified</pose>
        <truncated>0</truncated>
        <occluded>0</occluded>
        <difficult>0</difficult>
        <bndbox>
            <xmin>238</xmin>
            <ymin>197</ymin>
            <xmax>268</xmax>
            <ymax>224</ymax>
        </bndbox>
    </object>
    <object>
        <name>StNum</name>
        <pose>Unspecified</pose>
        <truncated>0</truncated>
        <occluded>0</occluded>
        <difficult>0</difficult>
        <bndbox>
            <xmin>19</xmin>
            <ymin>166</ymin>
            <xmax>81</xmax>
            <ymax>216</ymax>
        </bndbox>
    </object>
    <object>
        <name>AptNum</name>
        <pose>Unspecified</pose>
        <truncated>0</truncated>
        <occluded>0</occluded>
        <difficult>0</difficult>
        <bndbox>
            <xmin>244</xmin>
            <ymin>51</ymin>
            <xmax>306</xmax>
            <ymax>96</ymax>
        </bndbox>
    </object>
    <object>
        <name>Chamber</name>
        <pose>Unspecified</pose>
        <truncated>0</truncated>
        <occluded>0</occluded>
        <difficult>0</difficult>
        <polygon>
            <x1>198</x1>
            <y1>21</y1>
            <x2>206</x2>
            <y2>32</y2>
            <x3>217</x3>
            <y3>43</y3>
            <x4>227</x4>
            <y4>53</y4>
            <x5>234</x5>
            <y5>63</y5>
            <x6>240</x6>
            <y6>76</y6>
            <x7>244</x7>
            <y7>96</y7>
            <x8>244</x8>
            <y8>125</y8>
            <x9>242</x9>
            <y9>156</y9>
            <x10>238</x10>
            <y10>171</y10>
            <x11>235</x11>
            <y11>177</y11>
            <x12>229</x12>
            <y12>187</y12>
            <x13>223</x13>
            <y13>194</y13>
            <x14>217</x14>
            <y14>199</y14>
            <x15>165</x15>
            <y15>245</y15>
            <x16>158</x16>
            <y16>245</y16>
            <x17>103</x17>
            <y17>193</y17>
            <x18>95</x18>
            <y18>181</y18>
            <x19>87</x19>
            <y19>165</y19>
            <x20>84</x20>
            <y20>152</y20>
            <x21>83</x21>
            <y21>139</y21>
            <x22>83</x22>
            <y22>121</y22>
            <x23>84</x23>
            <y23>93</y23>
            <x24>88</x24>
            <y24>78</y24>
            <x25>93</x25>
            <y25>66</y25>
            <x26>100</x26>
            <y26>55</y26>
            <x27>107</x27>
            <y27>47</y27>
            <x28>116</x28>
            <y28>38</y28>
            <x29>124</x29>
            <y29>32</y29>
            <x30>131</x30>
            <y30>20</y30>
        </polygon>
    </object>
</annotation>