<annotation>
    <folder>First 10 rows</folder>
    <filename>BF_ST_000_APT_001Day0.jpg</filename>
    <size>
        <width>324</width>
        <height>300</height>
        <depth>3</depth>
    </size>
    <segmented>0</segmented>
    <object>
        <name>CellClump</name>
        <pose>Unspecified</pose>
        <truncated>0</truncated>
        <occluded>0</occluded>
        <difficult>0</difficult>
        <polygon>
            <x1>163</x1>
            <y1>262</y1>
            <x2>167</x2>
            <y2>263</y2>
            <x3>170</x3>
            <y3>268</y3>
            <x4>169</x4>
            <y4>274</y4>
            <x5>165</x5>
            <y5>277</y5>
            <x6>160</x6>
            <y6>277</y6>
            <x7>155</x7>
            <y7>275</y7>
            <x8>153</x8>
            <y8>271</y8>
            <x9>154</x9>
            <y9>265</y9>
            <x10>158</x10>
            <y10>263</y10>
        </polygon>
    </object>
    <object>
        <name>Cell</name>
        <pose>Unspecified</pose>
        <truncated>0</truncated>
        <occluded>0</occluded>
        <difficult>0</difficult>
        <polygon>
            <x1>163</x1>
            <y1>262</y1>
            <x2>167</x2>
            <y2>263</y2>
            <x3>170</x3>
            <y3>268</y3>
            <x4>169</x4>
            <y4>274</y4>
            <x5>165</x5>
            <y5>277</y5>
            <x6>160</x6>
            <y6>277</y6>
            <x7>155</x7>
            <y7>275</y7>
            <x8>153</x8>
            <y8>271</y8>
            <x9>154</x9>
            <y9>265</y9>
            <x10>158</x10>
            <y10>263</y10>
        </polygon>
    </object>
    <object>
        <name>Cell</name>
        <pose>Unspecified</pose>
        <truncated>0</truncated>
        <occluded>0</occluded>
        <difficult>0</difficult>
        <polygon>
            <x1>141</x1>
            <y1>38</y1>
            <x2>144</x2>
            <y2>41</y2>
            <x3>144</x3>
            <y3>44</y3>
            <x4>142</x4>
            <y4>48</y4>
            <x5>136</x5>
            <y5>49</y5>
            <x6>132</x6>
            <y6>46</y6>
            <x7>131</x7>
            <y7>42</y7>
            <x8>132</x8>
            <y8>39</y8>
            <x9>136</x9>
            <y9>37</y9>
        </polygon>
    </object>
    <object>
        <name>CellClump</name>
        <pose>Unspecified</pose>
        <truncated>0</truncated>
        <occluded>0</occluded>
        <difficult>0</difficult>
        <polygon>
            <x1>141</x1>
            <y1>38</y1>
            <x2>144</x2>
            <y2>41</y2>
            <x3>144</x3>
            <y3>44</y3>
            <x4>142</x4>
            <y4>48</y4>
            <x5>136</x5>
            <y5>49</y5>
            <x6>132</x6>
            <y6>46</y6>
            <x7>131</x7>
            <y7>42</y7>
            <x8>132</x8>
            <y8>39</y8>
            <x9>136</x9>
            <y9>37</y9>
        </polygon>
    </object>
    <object>
        <name>Channel</name>
        <pose>Unspecified</pose>
        <truncated>0</truncated>
        <occluded>0</occluded>
        <difficult>0</difficult>
        <polygon>
            <x1>324</x1>
            <y1>134</y1>
            <x2>288</x2>
            <y2>134</y2>
            <x3>274</x3>
            <y3>139</y3>
            <x4>261</x4>
            <y4>150</y4>
            <x5>255</x5>
            <y5>163</y5>
            <x6>254</x6>
            <y6>173</y6>
            <x7>255</x7>
            <y7>185</y7>
            <x8>258</x8>
            <y8>193</y8>
            <x9>266</x9>
            <y9>203</y9>
            <x10>276</x10>
            <y10>210</y10>
            <x11>287</x11>
            <y11>213</y11>
            <x12>301</x12>
            <y12>215</y12>
            <x13>306</x13>
            <y13>215</y13>
            <x14>308</x14>
            <y14>227</y14>
            <x15>301</x15>
            <y15>236</y15>
            <x16>161</x16>
            <y16>268</y16>
            <x17>25</x17>
            <y17>231</y17>
            <x18>18</x18>
            <y18>220</y18>
            <x19>18</x19>
            <y19>204</y19>
            <x20>13</x20>
            <y20>190</y20>
            <x21>8</x21>
            <y21>184</y21>
            <x22>1</x22>
            <y22>180</y22>
            <x23>1</x23>
            <y23>274</y23>
            <x24>35</x24>
            <y24>275</y24>
            <x25>41</x25>
            <y25>284</y25>
            <x26>41</x26>
            <y26>278</y26>
            <x27>45</x27>
            <y27>274</y27>
            <x28>54</x28>
            <y28>277</y28>
            <x29>137</x29>
            <y29>300</y29>
            <x30>183</x30>
            <y30>300</y30>
            <x31>269</x31>
            <y31>280</y31>
            <x32>276</x32>
            <y32>279</y32>
            <x33>281</x33>
            <y33>283</y33>
            <x34>282</x34>
            <y34>288</y34>
            <x35>289</x35>
            <y35>279</y35>
            <x36>323</x36>
            <y36>280</y36>
            <x37>324</x37>
            <y37>186</y37>
            <x38>319</x38>
            <y38>183</y38>
            <x39>311</x39>
            <y39>180</y39>
            <x40>293</x40>
            <y40>180</y40>
            <x41>290</x41>
            <y41>178</y41>
            <x42>289</x42>
            <y42>175</y42>
            <x43>289</x43>
            <y43>172</y43>
            <x44>291</x44>
            <y44>170</y44>
            <x45>293</x45>
            <y45>168</y45>
            <x46>324</x46>
            <y46>169</y46>
        </polygon>
    </object>
    <object>
        <name>Channel</name>
        <pose>Unspecified</pose>
        <truncated>0</truncated>
        <occluded>0</occluded>
        <difficult>0</difficult>
        <polygon>
            <x1>133</x1>
            <y1>31</y1>
            <x2>125</x2>
            <y2>40</y2>
            <x3>126</x3>
            <y3>34</y3>
            <x4>122</x4>
            <y4>31</y4>
            <x5>118</x5>
            <y5>30</y5>
            <x6>29</x6>
            <y6>51</y6>
            <x7>21</x7>
            <y7>59</y7>
            <x8>20</x8>
            <y8>82</y8>
            <x9>23</x9>
            <y9>85</y9>
            <x10>39</x10>
            <y10>85</y10>
            <x11>48</x11>
            <y11>88</y11>
            <x12>58</x12>
            <y12>93</y12>
            <x13>66</x13>
            <y13>102</y13>
            <x14>71</x14>
            <y14>110</y14>
            <x15>73</x15>
            <y15>119</y15>
            <x16>73</x16>
            <y16>129</y16>
            <x17>72</x17>
            <y17>137</y17>
            <x18>68</x18>
            <y18>143</y18>
            <x19>64</x19>
            <y19>150</y19>
            <x20>57</x20>
            <y20>156</y20>
            <x21>48</x21>
            <y21>161</y21>
            <x22>42</x22>
            <y22>163</y22>
            <x23>1</x23>
            <y23>163</y23>
            <x24>1</x24>
            <y24>130</y24>
            <x25>33</x25>
            <y25>130</y25>
            <x26>37</x26>
            <y26>128</y26>
            <x27>39</x27>
            <y27>123</y27>
            <x28>35</x28>
            <y28>118</y28>
            <x29>25</x29>
            <y29>118</y29>
            <x30>15</x30>
            <y30>118</y30>
            <x31>6</x31>
            <y31>115</y31>
            <x32>1</x32>
            <y32>110</y32>
            <x33>1</x33>
            <y33>20</y33>
            <x34>83</x34>
            <y34>1</y34>
            <x35>236</x35>
            <y35>1</y35>
            <x36>324</x36>
            <y36>25</y36>
            <x37>324</x37>
            <y37>117</y37>
            <x38>320</x38>
            <y38>113</y38>
            <x39>315</x39>
            <y39>107</y39>
            <x40>312</x40>
            <y40>99</y40>
            <x41>310</x41>
            <y41>90</y41>
            <x42>311</x42>
            <y42>66</y42>
            <x43>305</x43>
            <y43>57</y43>
            <x44>211</x44>
            <y44>32</y44>
            <x45>208</x45>
            <y45>33</y45>
            <x46>207</x46>
            <y46>36</y46>
            <x47>207</x47>
            <y47>40</y47>
            <x48>200</x48>
            <y48>32</y48>
        </polygon>
    </object>
    <object>
        <name>Trap</name>
        <pose>Unspecified</pose>
        <truncated>0</truncated>
        <occluded>0</occluded>
        <difficult>0</difficult>
        <bndbox>
            <xmin>135</xmin>
            <ymin>257</ymin>
            <xmax>191</xmax>
            <ymax>300</ymax>
        </bndbox>
    </object>
    <object>
        <name>Marker</name>
        <pose>Unspecified</pose>
        <truncated>0</truncated>
        <occluded>0</occluded>
        <difficult>0</difficult>
        <bndbox>
            <xmin>244</xmin>
            <ymin>212</ymin>
            <xmax>266</xmax>
            <ymax>233</ymax>
        </bndbox>
    </object>
    <object>
        <name>AptNum</name>
        <pose>Unspecified</pose>
        <truncated>0</truncated>
        <occluded>0</occluded>
        <difficult>0</difficult>
        <bndbox>
            <xmin>247</xmin>
            <ymin>61</ymin>
            <xmax>307</xmax>
            <ymax>109</ymax>
        </bndbox>
    </object>
    <object>
        <name>StNum</name>
        <pose>Unspecified</pose>
        <truncated>0</truncated>
        <occluded>0</occluded>
        <difficult>0</difficult>
        <bndbox>
            <xmin>17</xmin>
            <ymin>177</ymin>
            <xmax>81</xmax>
            <ymax>228</ymax>
        </bndbox>
    </object>
    <object>
        <name>Chamber</name>
        <pose>Unspecified</pose>
        <truncated>0</truncated>
        <occluded>0</occluded>
        <difficult>0</difficult>
        <polygon>
            <x1>165</x1>
            <y1>257</y1>
            <x2>226</x2>
            <y2>202</y2>
            <x3>233</x3>
            <y3>192</y3>
            <x4>241</x4>
            <y4>175</y4>
            <x5>245</x5>
            <y5>159</y5>
            <x6>245</x6>
            <y6>109</y6>
            <x7>241</x7>
            <y7>89</y7>
            <x8>236</x8>
            <y8>76</y8>
            <x9>222</x9>
            <y9>59</y9>
            <x10>211</x10>
            <y10>47</y10>
            <x11>206</x11>
            <y11>42</y11>
            <x12>199</x12>
            <y12>32</y12>
            <x13>132</x13>
            <y13>31</y13>
            <x14>124</x14>
            <y14>42</y14>
            <x15>109</x15>
            <y15>55</y15>
            <x16>96</x16>
            <y16>70</y16>
            <x17>87</x17>
            <y17>85</y17>
            <x18>83</x18>
            <y18>101</y18>
            <x19>82</x19>
            <y19>118</y19>
            <x20>83</x20>
            <y20>161</y20>
            <x21>87</x21>
            <y21>179</y21>
            <x22>97</x22>
            <y22>198</y22>
            <x23>115</x23>
            <y23>216</y23>
            <x24>135</x24>
            <y24>234</y24>
            <x25>158</x25>
            <y25>257</y25>
        </polygon>
    </object>
</annotation>